aor/__main__.py
aor/core.py
aor/fletgui.py
aor/main.py
aor/tkgui.py
aor/version.py
aor/assets/icon.png
all_of_resources-1.10.4.dist-info/LICENSE.md
all_of_resources-1.10.4.dist-info/LICENSE.让我们说中文.md
all_of_resources-1.10.4.dist-info/METADATA
all_of_resources-1.10.4.dist-info/WHEEL
all_of_resources-1.10.4.dist-info/entry_points.txt
all_of_resources-1.10.4.dist-info/top_level.txt
all_of_resources-1.10.4.dist-info/RECORD
