Metadata-Version: 2.2
Name: all-of-resources
Version: 1.10.4
Summary: 可以通过client.jar和.minecraft/assets下的松散文件提取Minecrafft的所有资源
Author: SystemFileB
Classifier: Programming Language :: Python :: 3
Classifier: License :: OSI Approved :: GNU Lesser General Public License v3 (LGPLv3)
Classifier: Operating System :: OS Independent
License-File: LICENSE.md
License-File: LICENSE.让我们说中文.md
Requires-Dist: flet>=0.27.0
Requires-Dist: flet-permission-handler
